polymarket_fetcher/__init__.py
polymarket_fetcher/config.py
polymarket_fetcher/api/__init__.py
polymarket_fetcher/api/client.py
polymarket_fetcher/api/endpoints.py
polymarket_fetcher/api/rate_limiter.py
polymarket_fetcher/callbacks/__init__.py
polymarket_fetcher/callbacks/dispatcher.py
polymarket_fetcher/callbacks/handlers.py
polymarket_fetcher/callbacks/models.py
polymarket_fetcher/extensions/__init__.py
polymarket_fetcher/extensions/base.py
polymarket_fetcher/fetcher/__init__.py
polymarket_fetcher/fetcher/incremental.py
polymarket_fetcher/fetcher/market_fetcher.py
polymarket_fetcher/fetcher/scheduler.py
polymarket_fetcher/matcher/__init__.py
polymarket_fetcher/matcher/keyword_matcher.py
polymarket_fetcher/models/__init__.py
polymarket_fetcher/models/market.py
polymarket_fetcher/models/sqlalchemy_types.py
polymarket_fetcher/scripts/init_db.py
polymarket_fetcher/storage/__init__.py
polymarket_fetcher/storage/database.py
polymarket_fetcher/storage/repositories/__init__.py
polymarket_fetcher/storage/repositories/market_repository.py
polymarket_fetcher-0.1.1.dist-info/METADATA
polymarket_fetcher-0.1.1.dist-info/WHEEL
polymarket_fetcher-0.1.1.dist-info/entry_points.txt
polymarket_fetcher-0.1.1.dist-info/RECORD
