Metadata-Version: 2.4
Name: polymarket-fetcher
Version: 0.1.1
Summary: Polymarket market data fetcher with scheduling, keyword matching, and event callbacks
Requires-Python: >=3.10
Requires-Dist: aiosqlite>=0.19.0
Requires-Dist: apscheduler>=3.10.0
Requires-Dist: greenlet>=3.0.0
Requires-Dist: httpx[socks]>=0.27.0
Requires-Dist: pydantic>=2.0
Requires-Dist: python-dateutil>=2.8.0
Requires-Dist: python-dotenv>=1.0.0
Requires-Dist: pyyaml>=6.0
Requires-Dist: sqlalchemy>=2.0.0
Requires-Dist: tenacity>=8.0
Provides-Extra: all
Requires-Dist: faker>=30.0.0; extra == 'all'
Requires-Dist: httpx-socks>=0.9.0; extra == 'all'
Requires-Dist: httpx>=0.27.0; extra == 'all'
Requires-Dist: pytest-asyncio>=0.21.0; extra == 'all'
Requires-Dist: pytest-cov>=4.0.0; extra == 'all'
Requires-Dist: pytest-mock>=3.10.0; extra == 'all'
Requires-Dist: pytest>=7.0.0; extra == 'all'
Provides-Extra: dev
Requires-Dist: faker>=30.0.0; extra == 'dev'
Requires-Dist: httpx>=0.27.0; extra == 'dev'
Requires-Dist: pytest-asyncio>=0.21.0; extra == 'dev'
Requires-Dist: pytest-cov>=4.0.0; extra == 'dev'
Requires-Dist: pytest-mock>=3.10.0; extra == 'dev'
Requires-Dist: pytest>=7.0.0; extra == 'dev'
Provides-Extra: socks
Requires-Dist: httpx-socks>=0.9.0; extra == 'socks'
